django_cpf_cnpj/__init__.py
django_cpf_cnpj/cnpj.py
django_cpf_cnpj/cpf.py
django_cpf_cnpj/fields.py
django_cpf_cnpj/forms.py
django_cpf_cnpj/validators.py
django_cpf_cnpj/widgets.py
django_cpf_cnpj/locale/pt_BR/LC_MESSAGES/django.mo
django_cpf_cnpj/locale/pt_BR/LC_MESSAGES/django.po
django_cpf_cnpj2-1.5.0.data/data/locale/django.mo
django_cpf_cnpj2-1.5.0.data/data/locale/django.po
django_cpf_cnpj2-1.5.0.dist-info/LICENSE
django_cpf_cnpj2-1.5.0.dist-info/METADATA
django_cpf_cnpj2-1.5.0.dist-info/WHEEL
django_cpf_cnpj2-1.5.0.dist-info/top_level.txt
django_cpf_cnpj2-1.5.0.dist-info/RECORD
