Metadata-Version: 2.1
Name: django-cpf-cnpj2
Version: 1.5.0
Summary: A django model and form field for normalised cpf and cnpj.
Home-page: https://github.com/elyasha/django-cpf-cnpj2
Author: elyasha
Author-email: matheuselyasha@gmail.com
License: MIT
Platform: OS Independent
Classifier: Framework :: Django
Classifier: Framework :: Django :: 2.2
Classifier: Framework :: Django :: 3.0
Classifier: Framework :: Django :: 3.1
Classifier: Framework :: Django :: 3.2
Classifier: Intended Audience :: Developers
Classifier: License :: OSI Approved :: MIT License
Classifier: Operating System :: OS Independent
Classifier: Programming Language :: Python :: 3
Classifier: Programming Language :: Python :: 3.6
Classifier: Programming Language :: Python :: 3.7
Classifier: Programming Language :: Python :: 3.8
Requires-Python: >=3.6
License-File: LICENSE
Requires-Dist: Django (>=2.2)
